{
  "type": "minecraft:crafting_shaped",
  "category": "misc",
  "key": {
    "B": "minecraft:blaze_rod",
    "E": "minecraft:egg",
    "S": "minecraft:fermented_spider_eye",
    "G": "minecraft:golden_sword"
  },
  "pattern": [
    " B ",
    " G ",
    "ESE"
  ],
  "result": {
    "id": "minecraft:golden_sword",
    "count": 1,
    "components": {
      "minecraft:item_name": { "text": "Pink Hero Weapon", "color": "#CC55AA", "italic": false },
      "minecraft:lore": [
        { "text": "Classic weapon for the brave hero", "color": "#AA1177", "italic": false }
      ],
      "minecraft:item_model": "theheroweapons:pinkweapon",
      "minecraft:max_damage": 25,
      "minecraft:attribute_modifiers": [
        {
          "id": "theheroweapons:pinkweapon.damage",
          "type": "minecraft:attack_damage",
          "amount": 106.0,
          "operation": "add_value",
          "slot": "mainhand"
        }
      ]
    }
  }
}